lzss.cpython-37m-darwin.so
lzss-0.3.dist-info/COPYING
lzss-0.3.dist-info/COPYING.LESSER
lzss-0.3.dist-info/METADATA
lzss-0.3.dist-info/WHEEL
lzss-0.3.dist-info/top_level.txt
lzss-0.3.dist-info/RECORD
