Metadata-Version: 2.1
Name: lzss
Version: 0.3
Summary: LZSS compression algorithm
Home-page: https://github.com/rumbah/pylzss
Author: Guillaume Tucker
Author-email: guillaume.tucker@plasticlogic.com
Maintainer: rumbah
Maintainer-email: rumbah@users.noreply.github.com
License: GNU LGPL v3
Platform: Windows
Platform: Linux
Classifier: Programming Language :: Python
Classifier: Programming Language :: Python :: 3
Classifier: Programming Language :: Python :: 2
Classifier: Topic :: System :: Archiving :: Compression
Classifier: Development Status :: 3 - Alpha
Classifier: License :: OSI Approved :: GNU Lesser General Public License v3 (LGPLv3)
